{
  "project_info": {
    "project_number": "945782441633",
    "project_id": "roiquery-test",
    "storage_bucket": "roiquery-test.appspot.com"
  },
  "client": [
    {
      "client_info": {
        "mobilesdk_app_id": "1:945782441633:android:98f0d688a4fa5880c952e0",
        "android_client_info": {
          "package_name": "com.nodetower.android_ad"
        }
      },
      "oauth_client": [
        {
          "client_id": "945782441633-rt57trfb1nomv30u3l8q7joce0787q9a.apps.googleusercontent.com",
          "client_type": 3
        }
      ],
      "api_key": [
        {
          "current_key": "AIzaSyDrE_1GCT43TZyHCbBcVLKl5KYFItTl9uI"
        }
      ],
      "services": {
        "appinvite_service": {
          "other_platform_oauth_client": [
            {
              "client_id": "945782441633-rt57trfb1nomv30u3l8q7joce0787q9a.apps.googleusercontent.com",
              "client_type": 3
            }
          ]
        }
      }
    }
  ],
  "configuration_version": "1"
}